libadalina_analytics/__init__.py
libadalina_analytics/clustering/__init__.py
libadalina_analytics/clustering/algorithms/__init__.py
libadalina_analytics/clustering/algorithms/zoning_algorithm.py
libadalina_analytics/clustering/algorithms/zoning_model.py
libadalina_analytics/clustering/algorithms/zoning_model_simple.py
libadalina_analytics/clustering/models/__init__.py
libadalina_analytics/clustering/models/adalina_zoning_algorithm_options.py
libadalina_analytics/clustering/models/adalina_zoning_data.py
libadalina_analytics/clustering/models/adalina_zoning_distance.py
libadalina_analytics/clustering/models/adalina_zoning_solution.py
libadalina_analytics/flows_distribution/__init__.py
libadalina_analytics/flows_distribution/algorithms/__init__.py
libadalina_analytics/flows_distribution/algorithms/flows_distribution_algorithm.py
libadalina_analytics/flows_distribution/algorithms/origin_destination_extractor.py
libadalina_analytics/flows_distribution/models/__init__.py
libadalina_analytics/relocation/__init__.py
libadalina_analytics/relocation/algorithms/__init__.py
libadalina_analytics/relocation/algorithms/adalina_algorithms.py
libadalina_analytics/relocation/algorithms/adalina_model_highs.py
libadalina_analytics/relocation/algorithms/adalina_relocation_algorithm.py
libadalina_analytics/relocation/models/__init__.py
libadalina_analytics/relocation/models/adalina_data.py
libadalina_analytics/relocation/models/adalina_model_type.py
libadalina_analytics/relocation/models/adalina_solution.py
libadalina_analytics/relocation/models/options.py
libadalina_analytics/relocation/models/relocation_resource.py
libadalina_analytics/utils/__init__.py
libadalina_analytics/utils/geometry_formats.py
libadalina_analytics/utils/timing.py
libadalina_analytics-1.1.9.dist-info/licenses/LICENSE
libadalina_analytics-1.1.9.dist-info/METADATA
libadalina_analytics-1.1.9.dist-info/WHEEL
libadalina_analytics-1.1.9.dist-info/top_level.txt
libadalina_analytics-1.1.9.dist-info/RECORD
