Metadata-Version: 2.4
Name: libadalina-analytics
Version: 1.1.9
Summary: A library for geoenrichment and analytics of geographic data
Author-email: Marco Casazza <d.marcocasazza@gmail.com>, Alberto Ceselli <alberto.ceselli@unimi.it>, Marco Premoli <marco.premoli@unimi.it>
License-Expression: MIT
Classifier: Development Status :: 3 - Alpha
Classifier: Intended Audience :: Developers
Classifier: Programming Language :: Python :: 3
Classifier: Programming Language :: Python :: 3.10
Requires-Python: ~=3.10
License-File: LICENSE
Requires-Dist: libadalina-core==1.3.4
Requires-Dist: highspy==1.11.0
Requires-Dist: pydantic==2.10.6
Requires-Dist: scikit-learn==1.7.0
Provides-Extra: dev
Requires-Dist: pytest==8.4.1; extra == "dev"
Requires-Dist: black; extra == "dev"
Requires-Dist: isort; extra == "dev"
Requires-Dist: sphinx; extra == "dev"
Requires-Dist: pydata-sphinx-theme; extra == "dev"
Requires-Dist: nbsphinx; extra == "dev"
Requires-Dist: sphinx-collections; extra == "dev"
Dynamic: license-file
